Workbook

Sheet PO
A1: 芯片型号 | B1: 时间 | C1: 贸易流 | D1: 价格保留四位小数（USD） | G1: 芯片型号 | H1: 单位芯片成本测算 | I1: 保留4位小数
A2: BM1398 | B2: 202608 | C2: Chanhua——>SG/HK | D2: 3.7699 | G2: BM1398 | H2: 3.7698884 | I2: =ROUND(H2,4) -> 3.7699 | J2: =A2=G2 -> TRUE | K2: =D2-I2 -> 0
A3: BM1746 | B3: 202608 | C3: Chanhua——>SG/HK | D3: 57.6365 | G3: BM1746 | H3: 57.636461 | I3: =ROUND(H3,4) -> 57.6365 | J3: =A3=G3 -> TRUE | K3: =D3-I3 -> 0
A4: BM1362 | B4: 202608 | C4: Chanhua——>SG/HK | D4: 2.4828 | G4: BM1362 | H4: 2.4828311 | I4: =ROUND(H4,4) -> 2.4828 | J4: =A4=G4 -> TRUE | K4: =D4-I4 -> 0
A5: BM1368+ | B5: 202608 | C5: Chanhua——>SG/HK | D5: 4.0901 | G5: BM1368+ | H5: 4.0900595 | I5: =ROUND(H5,4) -> 4.0901 | J5: =A5=G5 -> TRUE | K5: =D5-I5 -> 0
A6: BM1368 | B6: 202608 | C6: Chanhua——>SG/HK | D6: 5.0536 | G6: BM1368 | H6: 5.0536119 | I6: =ROUND(H6,4) -> 5.0536 | J6: =A6=G6 -> TRUE | K6: =D6-I6 -> 0
A7: BM1764 | B7: 202608 | C7: Chanhua——>SG/HK | D7: 3.5349 | G7: BM1764 | H7: 3.5349141 | I7: =ROUND(H7,4) -> 3.5349 | J7: =A7=G7 -> TRUE | K7: =D7-I7 -> 0
A8: BM1798 | B8: 202608 | C8: Chanhua——>SG/HK | D8: 200.2487 | G8: BM1798 | H8: 200.24868 | I8: =ROUND(H8,4) -> 200.2487 | J8: =A8=G8 -> TRUE | K8: =D8-I8 -> 0
A9: BM1489 | B9: 202608 | C9: Chanhua——>SG/HK | D9: 5.2113 | G9: BM1489 | H9: 5.2113185 | I9: =ROUND(H9,4) -> 5.2113 | J9: =A9=G9 -> TRUE | K9: =D9-I9 -> 0
A10: BM1366 | B10: 202608 | C10: Chanhua——>SG/HK | D10: 3.7914 | G10: BM1366 | H10: 3.7914498 | I10: =ROUND(H10,4) -> 3.7914 | J10: =A10=G10 -> TRUE | K10: =D10-I10 -> 0
A11: BM2100 | B11: 202608 | C11: Chanhua——>SG/HK | D11: 3.4623 | G11: BM2100 | H11: 3.4622811 | I11: =ROUND(H11,4) -> 3.4623 | J11: =A11=G11 -> TRUE | K11: =D11-I11 -> 0
A12: BM1727 | B12: 202608 | C12: Chanhua——>SG/HK | D12: 3.4712 | G12: BM1727 | H12: 3.4712061 | I12: =ROUND(H12,4) -> 3.4712 | J12: =A12=G12 -> TRUE | K12: =D12-I12 -> 0
A13: BM1766 | B13: 202608 | C13: Chanhua——>SG/HK | D13: 3.4712 | G13: BM1766 | H13: 3.4712061 | I13: =ROUND(H13,4) -> 3.4712 | J13: =A13=G13 -> TRUE | K13: =D13-I13 -> 0
... A28: BM2384 | B28: 202608 | C28: Chanhua——>SG/HK | D28: 7.8846 | G28: BM2384 | H28: 7.8845682 | I28: =ROUND(H28,4) -> 7.8846 | J28: =A28=G28 -> TRUE | K28: =D28-I28 -> 0
A29: BM1373 | B29: 202608 | C29: Chanhua——>SG/HK | D29: 28.4759 | E29: 更新 | G29: BM1373 | H29: 28.47588 | I29: =ROUND(H29,4) -> 28.4759 | J29: =A29=G29 -> TRUE | K29: =D29-I29 -> 0
A30: BM1493 | B30: 202608 | C30: Chanhua——>SG/HK | D30: 21.1352 | G30: BM1493 | H30: 21.135235 | I30: =ROUND(H30,4) -> 21.1352 | J30: =A30=G30 -> TRUE | K30: =D30-I30 -> 0
A31: BM1374 | B31: 202608 | C31: Chanhua——>SG/HK | D31: 37.6147 | E31: 更新 | G31: BM1374 | H31: 37.614658 | I31: =ROUND(H31,4) -> 37.6147 | J31: =A31=G31 -> TRUE | K31: =D31-I31 -> 0
A32: BM1376 | B32: 202608 | C32: Chanhua——>SG/HK | D32: 29.3258 | G32: BM1376 | H32: 29.325796 | I32: =ROUND(H32,4) -> 29.3258 | J32: =A32=G32 -> TRUE | K32: =D32-I32 -> 0
A33: BM2560 | B33: 202608 | C33: Chanhua——>SG/HK | D33: 6.4293486
A34: 1300 | B34: 202608 | C34: Chanhua——>SG/HK | D34: 36.826111

Sheet 价目表0701
A1: 产品上下文 | B1: 产品属性 | C1: 产品值 | D1: 产品说明 | E1: 单位 | F1: 主要单位 | G1: 行类型 | H1: 分段价格类型 | I1: 应用方法 | J1: 值 | K1: 动态公式 | L1: 静态公式 | M1: 起始日期 | N1: 终止日期 | O1: 优先顺序 | P1: [ ] | Q1: 型号
A2: 项目 | B2: 项目编号 | C2: Y31010513 | D2: BTC,BM1368PA芯片,FCLGA,6*8,ED,6mm x 8mm PKG size, 3L LGA ,exposed die，NSMD pad | E2: PCS | G2: 价目表行 | I2: 单价 | J2: 4.0901 | M2: 2024.05.01 | O2: 110 | P2: . | Q2: =VLOOKUP(C2,型号!A:C,3,0) -> BM1368+ | R2: =_xlfn.XLOOKUP(Q2,PO!A:A,PO!D:D,1,0) -> 4.0901 | S2: =R2-J2 -> 0
A3: 项目 | B3: 项目编号 | C3: Y31010515 | D3: BTC,BM1368PB芯片,FCLGA,6*8,ED,6mm x 8mm PKG size, 3L LGA ,exposed die，NSMD pad | E3: PCS | G3: 价目表行 | I3: 单价 | J3: 4.0901 | M3: 2024.05.01 | O3: 110 | P3: . | Q3: =VLOOKUP(C3,型号!A:C,3,0) -> BM1368+ | R3: =_xlfn.XLOOKUP(Q3,PO!A:A,PO!D:D,1,0) -> 4.0901 | S3: =R3-J3 -> 0
A4: 项目 | B4: 项目编号 | C4: Y31010506 | D4: BTC_BM1368AA,FCLGA,6*8,ED,6mm x 8mm PKG size, 3L LGA ,exposed die，NSMD pad | E4: PCS | G4: 价目表行 | I4: 单价 | J4: 5.0536 | M4: 2024.05.01 | O4: 110 | P4: . | Q4: =VLOOKUP(C4,型号!A:C,3,0) -> BM1368 | R4: =_xlfn.XLOOKUP(Q4,PO!A:A,PO!D:D,1,0) -> 5.0536 | S4: =R4-J4 -> 0
A5: 项目 | B5: 项目编号 | C5: Y31090501 | D5: 其他小币种,BM2380AA芯片,FCLGA,8*8,ED,molding, exposed die, high thermal EMC, 3L substrate | E5: PCS | G5: 价目表行 | I5: 单价 | J5: 2.2925 | M5: 2024.05.01 | O5: 110 | P5: . | Q5: =VLOOKUP(C5,型号!A:C,3,0) -> BM2380 | R5: =_xlfn.XLOOKUP(Q5,PO!A:A,PO!D:D,1,0) -> 2.2925 | S5: =R5-J5 -> 0
A6: 项目 | B6: 项目编号 | C6: Y09BM2042010 | D6: BM2042AA芯片-6mm x 6mm, molding, exposed die, CTM IO, 3L substrate | E6: PCS | G6: 价目表行 | I6: 单价 | J6: 3.4712 | M6: 2024.05.01 | O6: 110 | P6: . | Q6: =VLOOKUP(C6,型号!A:C,3,0) -> BM2042 | R6: =_xlfn.XLOOKUP(Q6,PO!A:A,PO!D:D,1,0) -> 3.4712 | S6: =R6-J6 -> 0
A7: 项目 | B7: 项目编号 | C7: Y09BM1366D10 | D7: BM1366AL芯片-6mm x 7mm, molding, exposed die, CTM IO, 30LD MP, serial power supply, 3L substrate | E7: PCS | G7: 价目表行 | I7: 单价 | J7: 3.7914 | M7: 2024.05.01 | O7: 110 | P7: . | Q7: =VLOOKUP(C7,型号!A:C,3,0) -> BM1366 | R7: =_xlfn.XLOOKUP(Q7,PO!A:A,PO!D:D,1,0) -> 3.7914 | S7: =R7-J7 -> 0
A8: 项目 | B8: 项目编号 | C8: Y30010511 | D8: BTC,BM1370晶圆,N3E,Fab18,BSL,N3E,Fab18，with PI,with Bumping，serial mode， | E8: PCS | G8: 价目表行 | I8: 单价 | J8: 0 | M8: 2024.05.01 | O8: 110 | P8: . | Q8: =VLOOKUP(C8,型号!A:C,3,0) -> BM1370晶圆 | R8: =_xlfn.XLOOKUP(Q8,PO!A:A,PO!D:D,1,0) -> 1 | S8: =R8-J8 -> 1
A9: 项目 | B9: 项目编号 | C9: Y31010518 | D9: BTC,BM1366BP芯片,FCLGA,6*8,BSM,6mm x 7mm, molding, exposed die, CTM IO,30LD MP, serial power supply, 3L substrate，BSM | E9: PCS | G9: 价目表行 | I9: 单价 | J9: 3.7914 | M9: 2024.05.01 | O9: 110 | P9: . | Q9: =VLOOKUP(C9,型号!A:C,3,0) -> BM1366 | R9: =_xlfn.XLOOKUP(Q9,PO!A:A,PO!D:D,1,0) -> 3.7914 | S9: =R9-J9 -> 0
A10: 项目 | B10: 项目编号 | C10: Y31010519 | D10: BTC,BM1370AA芯片,FCLGA,8*8,ED,8mm x 8mm PKG size, 3L LGA ,exposed die | E10: PCS | G10: 价目表行 | I10: 单价 | J10: 8.4438 | M10: 2024.05.01 | O10: 110 | P10: . | Q10: =VLOOKUP(C10,型号!A:C,3,0) -> BM1370 | R10: =_xlfn.XLOOKUP(Q10,PO!A:A,PO!D:D,1,0) -> 8.4438 | S10: =R10-J10 -> 0
A11: 项目 | B11: 项目编号 | C11: Y30020502 | D11: ETH,BM2282ST_WF晶圆,N22,Fab15,BSL,22nm, Fab15, total 49 layer， structure wafer | E11: PCS | G11: 价目表行 | I11: 单价 | J11: 0 | M11: 2024.05.01 | O11: 110 | P11: . | Q11: =VLOOKUP(C11,型号!A:C,3,0) -> BM2282晶圆 | R11: =_xlfn.XLOOKUP(Q11,PO!A:A,PO!D:D,1,0) -> 1 | S11: =R11-J11 -> 1
A12: 项目 | B12: 项目编号 | C12: Y30020501 | D12: ETH,BM2282_WF晶圆,N22,FAB15,BSL,22nm, Fab15, total 49 layer, real wafer | E12: PCS | G12: 价目表行 | I12: 单价 | J12: 0 | M12: 2024.05.01 | O12: 110 | P12: . | Q12: =VLOOKUP(C12,型号!A:C,3,0) -> BM2282晶圆 | R12: =_xlfn.XLOOKUP(Q12,PO!A:A,PO!D:D,1,0) -> 1 | S12: =R12-J12 -> 1
A13: 项目 | B13: 项目编号 | C13: Y30020503 | D13: ETH,BM2282AP晶圆,N25,AP,BSL,25nm，AP DRAM wafer | E13: PCS | G13: 价目表行 | I13: 单价 | J13: 0 | M13: 2024.05.01 | O13: 110 | P13: . | Q13: =VLOOKUP(C13,型号!A:C,3,0) -> BM2282晶圆 | R13: =_xlfn.XLOOKUP(Q13,PO!A:A,PO!D:D,1,0) -> 1 | S13: =R13-J13 -> 1
... A37: 项目 | B37: 项目编号 | C37: Y31010533 | D37: BTC,BM1370PM芯片,FCLGA,8*8mm,BSM,8mm x 8mm PKG size, 3L LGA ,exposed die,BSM | E37: PCS | G37: 价目表行 | I37: 单价 | J37: 8.4438 | M37: 2024.05.01 | O37: 110 | P37: . | Q37: =VLOOKUP(C37,型号!A:C,3,0) -> BM1370 | R37: =_xlfn.XLOOKUP(Q37,PO!A:A,PO!D:D,1,0) -> 8.4438 | S37: =R37-J37 -> 0

Sheet 价目表名称
A1: 1403 USD INT VAT0（下订单使用）

Sheet 历史
A2: 产品上下文 | B2: 产品属性 | C2: 产品值 | D2: 产品说明 | E2: 单位 | F2: 主要单位 | G2: 行类型 | H2: 分段价格类型 | I2: 应用方法 | J2: 值 | K2: 动态公式 | L2: 静态公式 | M2: 起始日期 | N2: 终止日期 | O2: 优先顺序 | P2: [ ] | Q2: 芯片类型
A3: 项目 | B3: 项目编号 | C3: Y31010513 | D3: BTC,BM1368PA芯片,FCLGA,6*8,ED,6mm x 8mm PKG size, 3L LGA ,exposed die，NSMD pad | E3: PCS | G3: 价目表行 | I3: 单价 | J3: 4.3874 | M3: 2021.09.14 | O3: 220 | P3: . | Q3: BM1368+ | R3: 4.382 | S3: =J3-R3 -> 0.0054
A4: 项目 | B4: 项目编号 | C4: Y31010515 | D4: BTC,BM1368PB芯片,FCLGA,6*8,ED,6mm x 8mm PKG size, 3L LGA ,exposed die，NSMD pad | E4: PCS | G4: 价目表行 | I4: 单价 | J4: 4.3874 | M4: 2021.09.14 | O4: 220 | P4: . | Q4: BM1368+ | R4: 4.382 | S4: =J4-R4 -> 0.0054
A5: 项目 | B5: 项目编号 | C5: Y31010506 | D5: BTC_BM1368AA,FCLGA,6*8,ED,6mm x 8mm PKG size, 3L LGA ,exposed die，NSMD pad | E5: PCS | G5: 价目表行 | I5: 单价 | J5: 5.4206 | M5: 2021.09.14 | O5: 220 | P5: . | Q5: BM1368 | R5: 5.4151 | S5: =J5-R5 -> 0.0055
A6: 项目 | B6: 项目编号 | C6: Y31090501 | D6: 其他小币种,BM2380AA芯片,FCLGA,8*8,ED,molding, exposed die, high thermal EMC, 3L substrate | E6: PCS | G6: 价目表行 | I6: 单价 | J6: 2.2925 | M6: 2021.09.14 | O6: 220 | P6: . | Q6: BM2380 | R6: 2.2925 | S6: =J6-R6 -> 0
A7: 项目 | B7: 项目编号 | C7: Y09BM2042010 | D7: BM2042AA芯片-6mm x 6mm, molding, exposed die, CTM IO, 3L substrate | E7: PCS | G7: 价目表行 | I7: 单价 | J7: 3.4623 | M7: 2021.09.14 | O7: 220 | P7: . | Q7: BM2100 | R7: 3.4623 | S7: =J7-R7 -> 0
A8: 项目 | B8: 项目编号 | C8: Y09BM1366D10 | D8: BM1366AL芯片-6mm x 7mm, molding, exposed die, CTM IO, 30LD MP, serial power supply, 3L substrate | E8: PCS | G8: 价目表行 | I8: 单价 | J8: 4.0649 | M8: 2021.09.14 | O8: 220 | P8: . | Q8: BM1366 | R8: 4.0649 | S8: =J8-R8 -> 0
A9: 项目 | B9: 项目编号 | C9: Y30010511 | D9: BTC,BM1370晶圆,N3E,Fab18,BSL,N3E,Fab18，with PI,with Bumping，serial mode， | E9: PCS | G9: 价目表行 | I9: 单价 | J9: 0 | M9: 2021.09.14 | O9: 220 | P9: . | Q9: BM1370 | R9: 8.5278 | S9: =J9-R9 -> -8.5278
A10: 项目 | B10: 项目编号 | C10: Y31010518 | D10: BTC,BM1366BP芯片,FCLGA,6*8,BSM,6mm x 7mm, molding, exposed die, CTM IO,30LD MP, serial power supply, 3L substrate，BSM | E10: PCS | G10: 价目表行 | I10: 单价 | J10: 4.0649 | M10: 2021.09.14 | O10: 220 | P10: . | Q10: BM1366 | R10: 4.0649 | S10: =J10-R10 -> 0
A11: 项目 | B11: 项目编号 | C11: Y31010519 | D11: BTC,BM1370AA芯片,FCLGA,8*8,ED,8mm x 8mm PKG size, 3L LGA ,exposed die | E11: PCS | G11: 价目表行 | I11: 单价 | J11: 8.5529 | M11: 2021.09.14 | O11: 220 | P11: . | Q11: BM1370 | R11: 8.5278 | S11: =J11-R11 -> 0.0251
A12: 项目 | B12: 项目编号 | C12: Y30020502 | D12: ETH,BM2282ST_WF晶圆,N22,Fab15,BSL,22nm, Fab15, total 49 layer， structure wafer | E12: PCS | G12: 价目表行 | I12: 单价 | J12: 5033.56 | M12: 2021.09.14 | O12: 220 | P12: . | Q12: BM2282 | R12: 0 | S12: =J12-R12 -> 5033.56
A13: 项目 | B13: 项目编号 | C13: Y30020501 | D13: ETH,BM2282_WF晶圆,N22,FAB15,BSL,22nm, Fab15, total 49 layer, real wafer | E13: PCS | G13: 价目表行 | I13: 单价 | J13: 5033.56 | M13: 2021.09.14 | O13: 220 | P13: . | Q13: BM2282 | R13: 0 | S13: =J13-R13 -> 5033.56
A14: 项目 | B14: 项目编号 | C14: Y30020503 | D14: ETH,BM2282AP晶圆,N25,AP,BSL,25nm，AP DRAM wafer | E14: PCS | G14: 价目表行 | I14: 单价 | J14: 1500 | M14: 2021.09.14 | O14: 220 | P14: . | Q14: BM2282 | R14: 0 | S14: =J14-R14 -> 1500
... A34: 项目 | B34: 项目编号 | C34: Y31010528 | D34: BTC,BM1372AA,FCLGA,12*13mm,exposedie,12mm x 13mm PKG size, 4L LGA ,exposed die | E34: PCS | G34: 价目表行 | I34: 单价 | J34: 31.5585 | M34: 2021.09.14 | O34: 220 | P34: . | Q34: BM1372 | R34: 31.8244 | S34: =J34-R34 -> -0.2659
A35: 项目 | B35: 项目编号 | C35: Y31010532 | D35: BTC,BM1372BB芯片,FCLGA,12*13mm,expose die,12mm x 13mm PKG size, 4L LGA ,exposed die | E35: PCS | G35: 价目表行 | I35: 单价 | J35: 31.5585 | M35: 2021.09.14 | O35: 220 | P35: . | Q35: #N/A | R35: 0 | S35: =J35-R35 -> 31.5585

Sheet 一揽子
A2: PO， | B2: 编号 | C2: 类型 | D2: 物料 | E2: 版本 | F2: 含税价格 | G2: 税率 | I2: 摘要 | J2: 单位 | K2: 数量 | L2: 价格 | M2: 最小包装（PCS） | N2: 交期（天） | O2: 品牌/厂商 | P2: MPN/原厂料号 | Q2: 供应商配置标识 | R2: 金额 | S2: 借记帐户 | T2: 保留 | | U2: 辅助 单位 | V2: 辅助 数量 | W2: 等级 | X2: 价目表价格 | Y2: 市场价格 | Z2: 价格类型 | AA2: 允许改写价格 | AB2: 价格限制 | AC2: 议价 | AD2: 合同 | AE2: 合同所属组织 | AF2: 原始单据：单据类型 | AG2: 原始单据：单据 | AH2: 原始单据：行 | AI2: 原始单据：所属组织 | AJ2: 供应商 报价单 | AK2: 合同 编号 | AL2: 版本 | AM2: 备注 | AN2: UN 编号 | AO2: UN 编号 说明 | AP2: 危险等级 | AQ2: 资本费用 | AR2: 事务处理性质 | AS2: 名字 | AT2: 姓氏 | AU2: 起始日期 | AV2: 终止日期 | AW2: 最小 发放额 | AX2: 议定 数量 | AY2: 议定 金额 | AZ2: 发放 数量 | BA2: 发放 金额 | BB2: 到期日 | BC2: 累计定价 | BD2: [ ]
A3: 202410100001 | B3: 1 | C3: 货物 | D3: Y31010519 | F3: 8.5278 | G3: 0 | H3: 00.00.00 | I3: BTC,BM1370AA芯片,FCLGA,8*8,ED,8mm x 8mm PKG size, 3L LGA ,exposed die | J3: 个 | K3: =VLOOKUP(D3,#REF!,15,0) -> #REF! | L3: 8.5278 | M3: =VLOOKUP(K3,PO!A:D,4,0) -> #REF! | N3: =L3-M3 -> #REF! | O3: 比特 | P3: 比特 | X3: 0 | AC3: * | BC3: * | BD3: ....
A4: 202410100002 | B4: 2 | C4: 货物 | D4: Y31010527 | F4: 8.5278 | G4: 0 | H4: 00.00.00 | I4: BTC,BM1370BC,FCLGA,8*8mm,exposedie,8mm x 8mm PKG size, 3L LGA ,exposed die | J4: 个 | K4: =VLOOKUP(D4,#REF!,15,0) -> #REF! | L4: 8.5278 | M4: =VLOOKUP(K4,PO!A:D,4,0) -> #REF! | N4: =L4-M4 -> #REF! | O4: 比特 | P4: 比特 | X4: 0 | AC4: * | BC4: * | BD4: ....
A5: 202410100003 | B5: 3 | C5: 货物 | D5: Y31010515 | F5: 5.4151 | G5: 0 | H5: 00.00.00 | I5: BTC,BM1368PB芯片,FCLGA,6*8,ED,6mm x 8mm PKG size, 3L LGA ,exposed die，NSMD pad | J5: 个 | K5: =VLOOKUP(D5,#REF!,15,0) -> #REF! | L5: 5.4151 | M5: =VLOOKUP(K5,PO!A:D,4,0) -> #REF! | N5: =L5-M5 -> #REF! | O5: 比特 | P5: 比特 | X5: 0 | AC5: * | BC5: * | BD5: ....
A6: 202410100004 | B6: 4 | C6: 货物 | D6: Y09BM1366D10 | F6: 4.0649 | G6: 0 | H6: 00.116.11601 | I6: BM1366AL芯片-6mm x 7mm, molding, exposed die, CTM IO, 30LD MP, serial power supply, 3L substrate | J6: 个 | K6: =VLOOKUP(D6,#REF!,15,0) -> #REF! | L6: 4.0649 | M6: =VLOOKUP(K6,PO!A:D,4,0) -> #REF! | N6: =L6-M6 -> #REF! | O6: 比特 | P6: 比特 | X6: 0 | AC6: * | BC6: * | BD6: ....
A7: 202410100005 | B7: 5 | C7: 货物 | D7: Y31010515 | F7: 4.382 | G7: 0 | H7: 00.00.00 | I7: BTC,BM1368PB芯片,FCLGA,6*8,ED,6mm x 8mm PKG size, 3L LGA ,exposed die，NSMD pad | J7: 个 | K7: =VLOOKUP(D7,#REF!,15,0) -> #REF! | L7: 4.382 | M7: =VLOOKUP(K7,PO!A:D,4,0) -> #REF! | N7: =L7-M7 -> #REF! | O7: 比特 | P7: 比特 | X7: 0 | AC7: * | BC7: * | BD7: ....
A8: 202410100006 | B8: 6 | C8: 货物 | D8: Y31010530 | F8: 8.5278 | G8: 0 | H8: 00.00.00 | I8: BTC,BM1370PA,FCLGA,8X8mm,exposedie,8mm x 8mm PKG size, 3L LGA ,exposed die | J8: 个 | K8: =VLOOKUP(D8,#REF!,15,0) -> #REF! | L8: 8.5278 | M8: =VLOOKUP(K8,PO!A:D,4,0) -> #REF! | N8: =L8-M8 -> #REF! | O8: 比特 | P8: 比特 | X8: 0 | AC8: * | BC8: * | BD8: ....
A9: 202410100007 | B9: 7 | C9: 货物 | D9: Y31010519 | F9: 8.5278 | G9: 0 | H9: 00.00.00 | I9: BTC,BM1370AA芯片,FCLGA,8*8,ED,8mm x 8mm PKG size, 3L LGA ,exposed die | J9: 个 | K9: =VLOOKUP(D9,#REF!,15,0) -> #REF! | L9: 8.5278 | M9: =VLOOKUP(K9,PO!A:D,4,0) -> #REF! | N9: =L9-M9 -> #REF! | O9: 比特 | P9: 比特 | X9: 0 | AC9: * | BC9: * | BD9: ....
A10: 202410100008 | B10: 8 | C10: 货物 | D10: Y31010527 | F10: 8.5278 | G10: 0 | H10: 00.00.00 | I10: BTC,BM1370BC,FCLGA,8*8mm,exposedie,8mm x 8mm PKG size, 3L LGA ,exposed die | J10: 个 | K10: =VLOOKUP(D10,#REF!,15,0) -> #REF! | L10: 8.5278 | M10: =VLOOKUP(K10,PO!A:D,4,0) -> #REF! | N10: =L10-M10 -> #REF! | O10: 比特 | P10: 比特 | X10: 0 | AC10: * | BC10: * | BD10: ....
A11: 202410100009 | B11: 9 | C11: 货物 | D11: Y31010515 | F11: 5.4151 | G11: 0 | H11: 00.00.00 | I11: BTC,BM1368PB芯片,FCLGA,6*8,ED,6mm x 8mm PKG size, 3L LGA ,exposed die，NSMD pad | J11: 个 | K11: =VLOOKUP(D11,#REF!,15,0) -> #REF! | L11: 5.4151 | M11: =VLOOKUP(K11,PO!A:D,4,0) -> #REF! | N11: =L11-M11 -> #REF! | O11: 比特 | P11: 比特 | X11: 0 | AC11: * | BC11: * | BD11: ....
A12: 202410100010 | B12: 10 | C12: 货物 | D12: Y31010506 | F12: 5.4151 | G12: 0 | H12: 00.116.11601 | I12: BTC_BM1368AA,FCLGA,6*8,ED,6mm x 8mm PKG size, 3L LGA ,exposed die，NSMD pad | J12: 个 | K12: =VLOOKUP(D12,#REF!,15,0) -> #REF! | L12: 5.4151 | M12: =VLOOKUP(K12,PO!A:D,4,0) -> #REF! | N12: =L12-M12 -> #REF! | O12: 比特 | P12: 比特 | X12: 0 | AC12: * | BC12: * | BD12: ....
A13: 202410100011 | B13: 11 | C13: 货物 | D13: Y31010520 | F13: 4.382 | G13: 0 | H13: 00.00.00 | I13: BTC,BM1368PV芯片,FCLGA,6*8mm,exposed die,6mm x 8mm PKG size, 3L LGA ,exposed die，NSMD pad | J13: 个 | K13: =VLOOKUP(D13,#REF!,15,0) -> #REF! | L13: 4.382 | M13: =VLOOKUP(K13,PO!A:D,4,0) -> #REF! | N13: =L13-M13 -> #REF! | O13: 比特 | P13: 比特 | X13: 0 | AC13: * | BC13: * | BD13: ....
A14: 202410100012 | B14: 12 | C14: 货物 | D14: Y31010521 | F14: 4.382 | G14: 0 | H14: 00.00.00 | I14: BTC,BM1368PM芯片,FCLGA,6*8mm,BSM,6mm x 8mm PKG size, 3L LGA ,exposed die，NSMD pad ,with BSM | J14: 个 | K14: =VLOOKUP(D14,#REF!,15,0) -> #REF! | L14: 4.382 | M14: =VLOOKUP(K14,PO!A:D,4,0) -> #REF! | N14: =L14-M14 -> #REF! | O14: 比特 | P14: 比特 | X14: 0 | AC14: * | BC14: * | BD14: ....
... A20: 202410100018 | B20: 18 | C20: 货物 | D20: Y31010515 | F20: 4.382 | G20: 0 | H20: 00.00.00 | I20: BTC,BM1368PB芯片,FCLGA,6*8,ED,6mm x 8mm PKG size, 3L LGA ,exposed die，NSMD pad | J20: 个 | K20: =VLOOKUP(D20,#REF!,15,0) -> #REF! | L20: 4.382 | M20: =VLOOKUP(K20,PO!A:D,4,0) -> #REF! | N20: =L20-M20 -> #REF! | O20: 比特 | P20: 比特 | X20: 0 | AC20: * | BC20: * | BD20: ....

Sheet 型号
A1: 产品值 | B1: 产品说明 | C1: 型号
A2: Y31010513 | B2: BTC,BM1368PA芯片,FCLGA,6*8,ED,6mm x 8mm PKG size, 3L LGA ,exposed die，NSMD pad | C2: BM1368+
A3: Y31010515 | B3: BTC,BM1368PB芯片,FCLGA,6*8,ED,6mm x 8mm PKG size, 3L LGA ,exposed die，NSMD pad | C3: BM1368+
A4: Y31010506 | B4: BTC_BM1368AA,FCLGA,6*8,ED,6mm x 8mm PKG size, 3L LGA ,exposed die，NSMD pad | C4: BM1368
A5: Y31090501 | B5: 其他小币种,BM2380AA芯片,FCLGA,8*8,ED,molding, exposed die, high thermal EMC, 3L substrate | C5: BM2380
A6: Y09BM2042010 | B6: BM2042AA芯片-6mm x 6mm, molding, exposed die, CTM IO, 3L substrate | C6: BM2042
A7: Y09BM1366D10 | B7: BM1366AL芯片-6mm x 7mm, molding, exposed die, CTM IO, 30LD MP, serial power supply, 3L substrate | C7: BM1366
A8: Y30010511 | B8: BTC,BM1370晶圆,N3E,Fab18,BSL,N3E,Fab18，with PI,with Bumping，serial mode， | C8: BM1370晶圆
A9: Y31010518 | B9: BTC,BM1366BP芯片,FCLGA,6*8,BSM,6mm x 7mm, molding, exposed die, CTM IO,30LD MP, serial power supply, 3L substrate，BSM | C9: BM1366
A10: Y31010519 | B10: BTC,BM1370AA芯片,FCLGA,8*8,ED,8mm x 8mm PKG size, 3L LGA ,exposed die | C10: BM1370
A11: Y30020502 | B11: ETH,BM2282ST_WF晶圆,N22,Fab15,BSL,22nm, Fab15, total 49 layer， structure wafer | C11: BM2282晶圆
A12: Y30020501 | B12: ETH,BM2282_WF晶圆,N22,FAB15,BSL,22nm, Fab15, total 49 layer, real wafer | C12: BM2282晶圆
... A37: Y31010533 | B37: BTC,BM1370PM芯片,FCLGA,8*8mm,BSM,8mm x 8mm PKG size, 3L LGA ,exposed die,BSM | C37: BM1370
